pymarkdown/.external-package
pymarkdown/__init__.py
pymarkdown/__main__.py
pymarkdown/api.py
pymarkdown/application_configuration_helper.py
pymarkdown/application_logging.py
pymarkdown/file_scan_helper.py
pymarkdown/main.py
pymarkdown/my_application_properties_facade.py
pymarkdown/py.typed
pymarkdown/return_code_helper.py
pymarkdown/version.py
pymarkdown/block_quotes/block_quote_count_helper.py
pymarkdown/block_quotes/block_quote_data.py
pymarkdown/block_quotes/block_quote_non_fenced_helper.py
pymarkdown/block_quotes/block_quote_processor.py
pymarkdown/coalesce/coalesce_processor.py
pymarkdown/container_blocks/container_block_leaf_processor.py
pymarkdown/container_blocks/container_block_nested_processor.py
pymarkdown/container_blocks/container_block_non_leaf_processor.py
pymarkdown/container_blocks/container_block_processor.py
pymarkdown/container_blocks/container_grab_bag.py
pymarkdown/container_blocks/container_helper.py
pymarkdown/container_blocks/container_indices.py
pymarkdown/container_blocks/parse_block_pass_properties.py
pymarkdown/extension_manager/__init__.py
pymarkdown/extension_manager/extension_impl.py
pymarkdown/extension_manager/extension_manager.py
pymarkdown/extension_manager/extension_manager_constants.py
pymarkdown/extension_manager/parser_extension.py
pymarkdown/extensions/__init__.py
pymarkdown/extensions/disallowed_raw_html.py
pymarkdown/extensions/extended_autolinks.py
pymarkdown/extensions/extension_one.py
pymarkdown/extensions/extension_token_types.py
pymarkdown/extensions/front_matter_extension.py
pymarkdown/extensions/front_matter_markdown_token.py
pymarkdown/extensions/markdown_strikethrough.py
pymarkdown/extensions/markdown_tables.py
pymarkdown/extensions/pragma_token.py
pymarkdown/extensions/task_list_items.py
pymarkdown/general/__init__.py
pymarkdown/general/bad_tokenization_error.py
pymarkdown/general/constants.py
pymarkdown/general/main_presentation.py
pymarkdown/general/parser_helper.py
pymarkdown/general/parser_logger.py
pymarkdownlnt-0.9.35.dist-info/licenses/LICENSE.txt
pymarkdownlnt-0.9.35.dist-info/METADATA
pymarkdownlnt-0.9.35.dist-info/WHEEL
pymarkdownlnt-0.9.35.dist-info/entry_points.txt
pymarkdownlnt-0.9.35.dist-info/top_level.txt
pymarkdownlnt-0.9.35.dist-info/RECORD
